yam_common/__init__.py
yam_common/motor_chain_robot.py
yam_common/mujoco_kdl.py
yam_common/utils.py
yam_common/dm/__init__.py
yam_common/dm/can_interface.py
yam_common/dm/dm.py
yam_common/dm/dm_driver.py
yam_common/dm/utils.py
yam_common-0.1.1.dist-info/METADATA
yam_common-0.1.1.dist-info/WHEEL
yam_common-0.1.1.dist-info/top_level.txt
yam_common-0.1.1.dist-info/RECORD
